MANIFEST.in
setup.py
django_orm/__init__.py
django_orm/apps/__init__.py
django_orm/apps/config.py
django_orm/apps/registry.py
django_orm/conf/__init__.py
django_orm/conf/global_settings.py
django_orm/conf/locale/__init__.py
django_orm/conf/locale/ar/__init__.py
django_orm/conf/locale/ar/formats.py
django_orm/conf/locale/ar_DZ/__init__.py
django_orm/conf/locale/ar_DZ/formats.py
django_orm/conf/locale/az/__init__.py
django_orm/conf/locale/az/formats.py
django_orm/conf/locale/bg/__init__.py
django_orm/conf/locale/bg/formats.py
django_orm/conf/locale/bn/__init__.py
django_orm/conf/locale/bn/formats.py
django_orm/conf/locale/bs/__init__.py
django_orm/conf/locale/bs/formats.py
django_orm/conf/locale/ca/__init__.py
django_orm/conf/locale/ca/formats.py
django_orm/conf/locale/cs/__init__.py
django_orm/conf/locale/cs/formats.py
django_orm/conf/locale/cy/__init__.py
django_orm/conf/locale/cy/formats.py
django_orm/conf/locale/da/__init__.py
django_orm/conf/locale/da/formats.py
django_orm/conf/locale/de/__init__.py
django_orm/conf/locale/de/formats.py
django_orm/conf/locale/de_CH/__init__.py
django_orm/conf/locale/de_CH/formats.py
django_orm/conf/locale/el/__init__.py
django_orm/conf/locale/el/formats.py
django_orm/conf/locale/en/__init__.py
django_orm/conf/locale/en/formats.py
django_orm/conf/locale/en_AU/__init__.py
django_orm/conf/locale/en_AU/formats.py
django_orm/conf/locale/en_GB/__init__.py
django_orm/conf/locale/en_GB/formats.py
django_orm/conf/locale/eo/__init__.py
django_orm/conf/locale/eo/formats.py
django_orm/conf/locale/es/__init__.py
django_orm/conf/locale/es/formats.py
django_orm/conf/locale/es_AR/__init__.py
django_orm/conf/locale/es_AR/formats.py
django_orm/conf/locale/es_CO/__init__.py
django_orm/conf/locale/es_CO/formats.py
django_orm/conf/locale/es_MX/__init__.py
django_orm/conf/locale/es_MX/formats.py
django_orm/conf/locale/es_NI/__init__.py
django_orm/conf/locale/es_NI/formats.py
django_orm/conf/locale/es_PR/__init__.py
djangorm.egg-info/PKG-INFO
djangorm.egg-info/SOURCES.txt
djangorm.egg-info/dependency_links.txt
djangorm.egg-info/requires.txt
djangorm.egg-info/top_level.txt