Metadata-Version: 2.1
Name: djangorm
Version: 0.1
Summary: Una biblioteca que contiene solo el ORM de Django
Home-page: UNKNOWN
Author: Tu nombre
Author-email: andresfelipe200004@gmail.com
License: UNKNOWN
Platform: UNKNOWN
